skoptom/__init__.py
skoptom/outlook.py
skoptom/rpalms.py
skoptom-0.7.dist-info/METADATA
skoptom-0.7.dist-info/WHEEL
skoptom-0.7.dist-info/top_level.txt
skoptom-0.7.dist-info/RECORD
