Metadata-Version: 2.1
Name: skoptom
Version: 0.7
Summary: This is SK Materials RPA package.
Home-page: https://github.com/dong5053/RPA
Author: DongHun Hwang
Author-email: dong5053@naver.com
License: UNKNOWN
Download-URL: https://github.com/dong5053/RPA/archive/refs/heads/main.zip
Keywords: SK Materials RPA Modules
Platform: UNKNOWN
Classifier: Programming Language :: Python :: 3
Classifier: Programming Language :: Python :: 3.2
Classifier: Programming Language :: Python :: 3.3
Classifier: Programming Language :: Python :: 3.4
Classifier: Programming Language :: Python :: 3.5
Classifier: Programming Language :: Python :: 3.6
Classifier: Programming Language :: Python :: 3.7
Classifier: Programming Language :: Python :: 3.8
Requires-Python: >=3
Requires-Dist: python-logstash
